coden_retriever/__init__.py
coden_retriever/__main__.py
coden_retriever/cli_metrics_contract.py
coden_retriever/config.py
coden_retriever/config_loader.py
coden_retriever/constants.py
coden_retriever/graph_utils.py
coden_retriever/pipeline.py
coden_retriever/token_estimator.py
coden_retriever/agent/__init__.py
coden_retriever/agent/coding_agent.py
coden_retriever/agent/commands.py
coden_retriever/agent/debug_logger.py
coden_retriever/agent/directory_browser.py
coden_retriever/agent/filtering_toolset.py
coden_retriever/agent/input_prompt.py
coden_retriever/agent/interactive_loop.py
coden_retriever/agent/mcp_server.py
coden_retriever/agent/model_factory.py
coden_retriever/agent/models.py
coden_retriever/agent/permission_toolset.py
coden_retriever/agent/prompt_builder.py
coden_retriever/agent/query_executor.py
coden_retriever/agent/react_loop.py
coden_retriever/agent/response_renderer.py
coden_retriever/agent/rich_console.py
coden_retriever/agent/starter_questions.py
coden_retriever/agent/stream_handler.py
coden_retriever/agent/text_tool_fallback.py
coden_retriever/agent/tool_instructions.py
coden_retriever/agent/tool_permission_picker.py
coden_retriever/agent/tool_picker.py
coden_retriever/agent/tool_wizard.py
coden_retriever/agent/ui_utils.py
coden_retriever/cache/__init__.py
coden_retriever/cache/graph_building.py
coden_retriever/cache/manager.py
coden_retriever/cache/models.py
coden_retriever/clone/__init__.py
coden_retriever/clone/combined.py
coden_retriever/clone/semantic.py
coden_retriever/clone/sparse_utils.py
coden_retriever/clone/syntactic.py
coden_retriever/clone/tokenizer.py
coden_retriever/daemon/__init__.py
coden_retriever/daemon/client.py
coden_retriever/daemon/handlers.py
coden_retriever/daemon/project_cache.py
coden_retriever/daemon/protocol.py
coden_retriever/daemon/server.py
coden_retriever/dead_code/__init__.py
coden_retriever/dead_code/confidence.py
coden_retriever/dead_code/detector.py
coden_retriever/formatters/__init__.py
coden_retriever-1.2.0.dist-info/METADATA
coden_retriever-1.2.0.dist-info/WHEEL
coden_retriever-1.2.0.dist-info/entry_points.txt
coden_retriever-1.2.0.dist-info/top_level.txt
coden_retriever-1.2.0.dist-info/RECORD
