Metadata-Version: 2.4
Name: coden-retriever
Version: 1.2.0
Summary: Retriever for finding most relevant code
License: MIT
Requires-Python: <3.13,>=3.10
Requires-Dist: networkx>=3.0
Requires-Dist: tree-sitter<0.24,>=0.23.0
Requires-Dist: tree-sitter-languages>=1.10.0
Requires-Dist: pydantic>=2.0.0
Requires-Dist: rich>=13.0.0
Requires-Dist: prompt_toolkit>=3.0.0
Requires-Dist: tiktoken>=0.5.0
Requires-Dist: tokenizers>=0.15.0
Requires-Dist: watchdog>=4.0.0
Provides-Extra: semantic
Requires-Dist: model2vec>=0.1.0; extra == "semantic"
Requires-Dist: numpy; extra == "semantic"
Requires-Dist: scipy>=1.10.0; extra == "semantic"
Provides-Extra: mcp
Requires-Dist: fastmcp>=0.1.0; extra == "mcp"
Provides-Extra: agent
Requires-Dist: pydantic-ai-slim[mcp,openai]>=0.1.0; extra == "agent"
Requires-Dist: fastmcp>=0.1.0; extra == "agent"
Provides-Extra: all
Requires-Dist: coden-retriever[agent,mcp,semantic]; extra == "all"
Provides-Extra: dev
Requires-Dist: pytest>=9.0.0; extra == "dev"
Requires-Dist: pytest-asyncio>=1.3.0; extra == "dev"
Requires-Dist: ruff>=0.1.0; extra == "dev"
Requires-Dist: httpx>=0.27.0; extra == "dev"
Requires-Dist: debugpy>=1.8.0; extra == "dev"
Provides-Extra: dynamic-tools
